vk_sdk/__init__.py
vk_sdk/cmd.py
vk_sdk/database.py
vk_sdk/events.py
vk_sdk/imports.py
vk_sdk/keyboard.py
vk_sdk/lp.py
vk_sdk/methodExecutor.py
vk_sdk/thread.py
vk_sdk/timeExtension.py
vk_sdk/user.py
vk_sdk/wait.py
vk_sdk-1.10.2.dist-info/LICENSE
vk_sdk-1.10.2.dist-info/METADATA
vk_sdk-1.10.2.dist-info/WHEEL
vk_sdk-1.10.2.dist-info/entry_points.txt
vk_sdk-1.10.2.dist-info/top_level.txt
vk_sdk-1.10.2.dist-info/RECORD
