Metadata-Version: 2.1
Name: vk-sdk
Version: 1.10.2
Summary: Wrapper around vk_api library
Home-page: https://github.com/SPRAVEDLIVO/VK-SDK
Author: SPRAVEDLIVO
Author-email: admin@spravedlivo.dev
License: AGPLv3
Classifier: Programming Language :: Python :: 3.10
Classifier: License :: OSI Approved :: GNU Affero General Public License v3 or later (AGPLv3+)
Classifier: Operating System :: OS Independent
Requires-Python: >=3.10
License-File: LICENSE
Requires-Dist: pytz
Requires-Dist: vk-api
